malmoext/Agent.py
malmoext/AgentInventory.py
malmoext/Inventory.py
malmoext/Logger.py
malmoext/MalmoPython.lib
malmoext/MalmoPython.pyd
malmoext/MalmoPython.so
malmoext/MissionBuilder.py
malmoext/Performance.py
malmoext/Statistics.py
malmoext/Utils.py
malmoext/__init__.py
malmoext/malmoutils.py
malmoext-37.1.0.dist-info/LICENSE
malmoext-37.1.0.dist-info/METADATA
malmoext-37.1.0.dist-info/WHEEL
malmoext-37.1.0.dist-info/top_level.txt
malmoext-37.1.0.dist-info/RECORD
