Metadata-Version: 2.1
Name: malmoext
Version: 37.1.0
Summary: An extension to Microsoft's Malmo Project
Home-page: https://github.com/naterex/malmo-extension
Author: Nathaniel Rex
Author-email: nathanieljrex@gmail.com
License: UNKNOWN
Platform: UNKNOWN
Classifier: Programming Language :: Python :: 3
Classifier: License :: OSI Approved :: MIT License
Classifier: Operating System :: OS Independent
